dagster_uc/__init__.py
dagster_uc/config.py
dagster_uc/configmaps.py
dagster_uc/log.py
dagster_uc/manage_user_code_deployments.py
dagster_uc/uc_handler.py
dagster_uc/utils.py
dagster_uc/_helm/__init__.py
dagster_uc/_helm/client.py
dagster_uc/_helm/command.py
dagster_uc/_helm/errors.py
dagster_uc/_helm/models.py
dagster_uc-0.6.6.dist-info/METADATA
dagster_uc-0.6.6.dist-info/WHEEL
dagster_uc-0.6.6.dist-info/entry_points.txt
dagster_uc-0.6.6.dist-info/licenses/LICENSE
dagster_uc-0.6.6.dist-info/RECORD
