Metadata-Version: 2.4
Name: dagster-uc
Version: 0.6.6
Summary: CLI for managing user code deployments of a Dagster instance that was deployed on kubernetes.
Project-URL: Homepage, https://github.com/ASML-Labs/dagster-uc
Project-URL: Issues, https://github.com/ASML-Labs/dagster-uc/issues
Author: Stefan Verbruggen, Ion Koutsouris
License-File: LICENSE
Classifier: License :: OSI Approved :: Apache Software License
Classifier: Programming Language :: Python :: 3.9
Classifier: Programming Language :: Python :: 3.10
Classifier: Programming Language :: Python :: 3.11
Classifier: Programming Language :: Python :: 3.12
Classifier: Programming Language :: Python :: 3.13
Requires-Python: >=3.9
Requires-Dist: kr8s<1.0,>=0.20.1
Requires-Dist: packaging>=25.0
Requires-Dist: pydantic-settings>=2
Requires-Dist: pydantic>=2
Requires-Dist: pytz
Requires-Dist: pyyaml
Requires-Dist: tomli
Requires-Dist: typer>=0.15.1
